pyclvm/__init__.py
pyclvm/_clvm.py
pyclvm/connect.py
pyclvm/login.py
pyclvm/plt.py
pyclvm/_common/__init__.py
pyclvm/_common/azure_instance_mapping.py
pyclvm/_common/azure_instance_proxy.py
pyclvm/_common/azure_rest_api.py
pyclvm/_common/gcp_instance_mapping.py
pyclvm/_common/gcp_instance_proxy.py
pyclvm/_common/session_aws.py
pyclvm/_common/session_azure.py
pyclvm/_common/session_gcp.py
pyclvm/_common/signal_handler.py
pyclvm/_common/user_data.py
pyclvm/configure/__init__.py
pyclvm/configure/aws.py
pyclvm/install/__init__.py
pyclvm/install/aws.py
pyclvm/instance/__init__.py
pyclvm/instance/_mapping.py
pyclvm/instance/_process.py
pyclvm/instance/command.py
pyclvm/instance/ls.py
pyclvm/instance/start.py
pyclvm/instance/stop.py
pyclvm/redirect/__init__.py
pyclvm/redirect/start.py
pyclvm/redirect/stop.py
pyclvm/ssh/__init__.py
pyclvm/ssh/new.py
pyclvm/ssh/restore.py
pyclvm/ssh/start.py
pyclvm/ssm/__init__.py
pyclvm/ssm/clear.py
pyclvm/ssm/shell.py
pyclvm/ssm/session/__init__.py
pyclvm/ssm/session/ls.py
pyclvm/ssm/session/start.py
pyclvm/ssm/session/stop.py
pyclvm/vscode/__init__.py
pyclvm/vscode/adjust.py
pyclvm/vscode/install.py
pyclvm/vscode/start.py
pyclvm-1.1.11.dist-info/entry_points.txt
pyclvm-1.1.11.dist-info/LICENSE.md
pyclvm-1.1.11.dist-info/WHEEL
pyclvm-1.1.11.dist-info/METADATA
pyclvm-1.1.11.dist-info/RECORD
