Metadata-Version: 2.1
Name: pyclvm
Version: 1.1.11
Summary: Command Line Utility to connect or redirect ports to a Cloud Virtual Machine
Author-email: BST Labs <bstlabs@caios.io>
Requires-Python: >=3.8
Classifier: License :: OSI Approved :: MIT License
Requires-Dist: boto3 >= 1.18.42
Requires-Dist: dynacli >= 1.0.8
Requires-Dist: pyjdict >= 1.0.6
Requires-Dist: psutil >= 5.9.0
Requires-Dist: rich >= 12.0.1
Requires-Dist: pycryptodome >= 3.14.1
Requires-Dist: google-cloud-compute >= 1.3.2
Requires-Dist: google-cloud-pubsub >= 2.13.6
Requires-Dist: ec2map >= 1.0.12
Requires-Dist: singleton-decorator >= 1.0.0
Requires-Dist: azure-core >= 1.24.1
Requires-Dist: azure-common >= 1.1.28
Requires-Dist: azure-identity >= 1.10.0
Requires-Dist: azure-mgmt-core >= 1.3.1
Requires-Dist: azure-mgmt-compute >= 27.1.0
Requires-Dist: azure-mgmt-subscription >= 3.1.1
Requires-Dist: oauthlib >= 3.2.0
Requires-Dist: backoff >= 2.1.2
Requires-Dist: commentjson >= 0.9.0
Requires-Dist: configparser >= 5.2.0
Requires-Dist: black >=22.3.0 ; extra == "dev"
Requires-Dist: pylint >=2.12.2 ; extra == "dev"
Requires-Dist: isort >=5.9.3 ; extra == "dev"
Requires-Dist: autoflake >=1.4 ; extra == "dev"
Requires-Dist: flake8 >=4.0.1 ; extra == "dev"
Requires-Dist: pre-commit >=2.17.0 ; extra == "dev"
Requires-Dist: mkdocs-material >=8.1.2 ; extra == "doc"
Requires-Dist: pytest >=5.4.3 ; extra == "test"
Project-URL: Changelog, https://github.com/BstLabs/py-clvm/blob/main/CHANGELOG.md
Project-URL: Home, https://github.com/bstlabs/py-clvm
Project-URL: Source, https://github.com/bstlabs/py-clvm
Provides-Extra: dev
Provides-Extra: doc
Provides-Extra: gui
Provides-Extra: test
